importhelper/__init__.py
importhelper-0.0.5.dist-info/LICENSE
importhelper-0.0.5.dist-info/METADATA
importhelper-0.0.5.dist-info/WHEEL
importhelper-0.0.5.dist-info/top_level.txt
importhelper-0.0.5.dist-info/RECORD
