Metadata-Version: 2.1
Name: importhelper
Version: 0.0.5
Summary: Lets you import stuff ezier
Home-page: https://github.com/The0therPenguin/importhelper
Author: The0therPenguin
Author-email: ykwfhp@gmail.com
License: UNKNOWN
Project-URL: Bug Tracker, https://github.com/The0therPenguin/importhelper/issues
Platform: UNKNOWN
Classifier: Programming Language :: Python :: 3
Classifier: License :: OSI Approved :: MIT License
Classifier: Operating System :: OS Independent
Requires-Python: >=2.6
License-File: LICENSE
